jupyter_server_kernels/__init__.py
jupyter_server_kernels/app.py
jupyter_server_kernels/gateway/__init__.py
jupyter_server_kernels/gateway/gateway_client.py
jupyter_server_kernels/gateway/handlers.py
jupyter_server_kernels/gateway/managers.py
jupyter_server_kernels/kernels/__init__.py
jupyter_server_kernels/kernels/handlers.py
jupyter_server_kernels/kernels/kernelmanager.py
jupyter_server_kernels/kernels/websocket.py
jupyter_server_kernels/kernels/connection/__init__.py
jupyter_server_kernels/kernels/connection/abc.py
jupyter_server_kernels/kernels/connection/base.py
jupyter_server_kernels/kernels/connection/channels.py
jupyter_server_kernels/kernelspecs/__init__.py
jupyter_server_kernels/kernelspecs/handlers.py
jupyter_server_kernels/sessions/__init__.py
jupyter_server_kernels/sessions/handlers.py
jupyter_server_kernels/sessions/sessionmanager.py
jupyter_server_kernels-0.1.2.data/data/etc/jupyter/jupyter_server_config.d/jupyter_server_kernels.json
jupyter_server_kernels-0.1.2.dist-info/METADATA
jupyter_server_kernels-0.1.2.dist-info/WHEEL
jupyter_server_kernels-0.1.2.dist-info/licenses/LICENSE
jupyter_server_kernels-0.1.2.dist-info/RECORD
