Metadata-Version: 2.1
Name: jupyter_server_kernels
Version: 0.1.2
Summary: A Jupyter Server Extension Providing Kernels.
Project-URL: Homepage, https://jupyter.org
Author-email: Jupyter Development Team <jupyter@googlegroups.com>
License: # Licensing terms
License-File: LICENSE
Keywords: ipython,jupyter
Classifier: Intended Audience :: Developers
Classifier: Intended Audience :: Science/Research
Classifier: Intended Audience :: System Administrators
Classifier: License :: OSI Approved :: BSD License
Classifier: Programming Language :: Python
Classifier: Programming Language :: Python :: 3.8
Classifier: Programming Language :: Python :: 3.9
Classifier: Programming Language :: Python :: 3.10
Classifier: Programming Language :: Python :: 3.11
Requires-Python: >=3.8
Requires-Dist: jupyter-client>=7.4.4
Requires-Dist: jupyter-core!=~5.0,>=4.12
Requires-Dist: tornado>=6.2.0
Requires-Dist: traitlets>=5.3.0
